<?xml version="1.0" ?>
	<item class="K01_Item" name="shg51_oc04_gp01_d" type="attachment" view_settings="objects/attachments/gp07/gp07.xml">
		<description_ingame text="@ui_shg51_gp01_d_ingame"/>
		<skins>
			<material name="default"/>
			<material name="oc04"/>
		</skins>
		<UI_stats>
			<param name="name" value="@shg51_gp01_d_name"/>
			<param name="description" value="@ui_shg51_gp01_d"/>
			<param name="icon" value="ar29_oc04_gp_d"/>
		</UI_stats>
		<mmo_stats>
			<param name="item_category" value="attachment"/>
			<param name="shopcontent" value="1"/>
			<param name="classes" value="M"/>
		</mmo_stats>
		<drop_params>
			<item name="shg51_oc04_gp01_d" type="attachment"/>
		</drop_params>
		<settings>
			<param name="reload_duration_mul" value="0.9"/>
			<param name="select_duration_mul" value="0.8"/>
			<param name="deselect_duration_mul" value="0.8"/>
		</settings>
		<types>
			<type helper="underbarrel_large" name="shg51_oc04_gp01_d"/>
		</types>
	</item>